waterhealer/__init__.py
waterhealer/checker.py
waterhealer/core.py
waterhealer/dask.py
waterhealer/dask_plugin.py
waterhealer/function.py
waterhealer/healing.py
waterhealer/kafka.py
waterhealer/source.py
water_healer-0.1.8.dist-info/METADATA
water_healer-0.1.8.dist-info/WHEEL
water_healer-0.1.8.dist-info/top_level.txt
water_healer-0.1.8.dist-info/RECORD
