Metadata-Version: 2.1
Name: water-healer
Version: 0.1.8
Summary: Extension of Kafka Streamz to update consumer offset for successful sink
Home-page: https://github.com/huseinzol05/water-healer
Author: huseinzol05
Author-email: husein.zol05@gmail.com
License: MIT
Platform: UNKNOWN
Classifier: Programming Language :: Python :: 3.7
Classifier: Intended Audience :: Developers
Classifier: License :: OSI Approved :: MIT License
Classifier: Operating System :: OS Independent
Requires-Python: >=3.7.*
Requires-Dist: APScheduler
Requires-Dist: confluent-kafka
Requires-Dist: expiringdict
Requires-Dist: graphviz
Requires-Dist: json-logging
Requires-Dist: networkx (==2.3)
Requires-Dist: prometheus-client
Requires-Dist: redis
Requires-Dist: redis-collections
Requires-Dist: streamz (==0.5.2)
Requires-Dist: tornado
